[{"organisation":"Legal Insider","year":2025,"award":"Boutique Insurance Law Firm of the Year - London 2025"},{"organisation":"Lexology formerly Who’s Who Legal","year":2025,"award":"Thought Leader recommended for Insurance - Stephen Carter / Bernadette Bailey"},{"organisation":"Leaders League","year":2025,"award":"Claims & Insurance Litigation - Recommended"},{"organisation":"Global 100","year":2025,"award":"Insurance & Reinsurance Law Firm of the Year UK 2025"},{"organisation":"Worldwide Financial Advisor Continent Awards","year":2025,"award":"UK Reinsurance Law Firm of the Year UK"},{"organisation":"Global Law Experts","year":2025,"award":"Insurance & Reinsurance Law Firm of the Year in England"},{"organisation":"Chambers Guide UK & Chambers Global","year":2025,"award":"Leading Firm in Insurance:  Contentious Claims & Reinsurance"},{"organisation":"Chambers Global","year":2025,"award":"Insuralex – Leading Multi-Jurisdictional Network"},{"organisation":"Lawyers International’s Legal 100","year":2025,"award":"Insurance & Reinsurance Law Firm of the Year – UK"},{"organisation":"Lawyers Worldwide Awards","year":2025,"award":"Super Lawyers 2026"},{"organisation":"ACQ Five Awards","year":2025,"award":"United Kingdom – Lawyer of the Year (Insurance Litigation) – Stephen Carter"},{"organisation":"M&A Today","year":2025,"award":"Insurance & Reinsurance Law Firm of the Year"},{"organisation":"Lawyers Worldwide Magazine","year":2025,"award":"Reinsurance Law Firm of the Year – Law Firm of the Year Awards"},{"organisation":"Corporate International","year":2025,"award":"Insurance & Reinsurance Law Firm of the Year in England 2025"},{"organisation":"Lawyers Worldwide Annual Awards","year":2025,"award":"UK Reinsurance Law Firm of the Year"},{"organisation":"Global Business Awards","year":2025,"award":"Best Insurance Litigators UK"},{"organisation":"Corporate Livewire Innovation & Excellence Awards","year":2025,"award":"Insurance Law Firm of the Year"},{"organisation":"Superior Lawyers 2025","year":2025,"award":"Insurance & Reinsurance Law Firm of the Year"},{"organisation":"Global Leading Lawyers Awards","year":2025,"award":"UK Reinsurance Law Firm of the Year"},{"organisation":"Legal Expert Worldwide Awards","year":2025,"award":"UK Reinsurance Law Firm of the Year"},{"organisation":"Lawyer Network Annual Awards","year":2025,"award":"Insurance & Reinsurance Law Firm of the Year in England"},{"organisation":"5 Star Lawyers Awards","year":2025,"award":"Insurance & Reinsurance Law Firm of the Year UK"},{"organisation":"Leading Lawyers Worldwide 2025","year":2025,"award":"UK Reinsurance Law Firm of the Year Award"},{"organisation":"Chambers Guide, UK","year":2025,"award":"Leading Lawyer:  Contentious Claims & Reinsurance – Stephen Carter"},{"organisation":"Global Law Experts Awards","year":2025,"award":"Insurance & Reinsurance Law Firm of the Year"},{"organisation":"ACQ5 Global Awards","year":2025,"award":"UK – Insurance & Reinsurance Law Firm of the Year"},{"organisation":"ACQ5 Global Awards","year":2025,"award":"UK – Insurance & Reinsurance Lawyer of the Year – Stephen Carter"},{"organisation":"Legal Insider","year":2024,"award":"Boutique Insurance Law Firm of the  Year – London 2025 - Stephen Carter / Bernadette Bailey"},{"organisation":"Lexology formerly Who’s Who Legal","year":2024,"award":"Recommended  for Insurance & Reinsurance – Stephen Carter / Bernadette Bailey"},{"organisation":"Leaders League","year":2024,"award":"Claims & Insurance Litigation"},{"organisation":"Global 100","year":2024,"award":"Insurance & Reinsurance Law Firm of the Year UK"},{"organisation":"Corporate America Today Awards","year":2024,"award":"Insurance & Reinsurance Law Firm of the Year UK"},{"organisation":"Worldwide Financial Advisor Continent Awards","year":2024,"award":"UK Reinsurance Law Firm of the Year UK"},{"organisation":"Global Law Experts","year":2024,"award":"Insurance & Reinsurance Law Firm of the Year in England"},{"organisation":"Chambers Guide UK & Chambers Global","year":2024,"award":"Leading Firm in Insurance:  Contentious Claims & Reinsurance"},{"organisation":"Chambers Global","year":2024,"award":"Insuralex – Leading Multi-Jurisdictional Network"},{"organisation":"Lawyers International’s Legal 100","year":2024,"award":"Insurance & Reinsurance Law Firm of the Year – UK"},{"organisation":"Lawyers Worldwide Awards","year":2024,"award":"Super Lawyers 2025"},{"organisation":"ACQ Five Awards","year":2024,"award":"United Kingdom – Lawyer of the Year (Insurance Litigation) – Stephen Carter"},{"organisation":"M&A Today","year":2024,"award":"Insurance & Reinsurance Law Firm of the Year"},{"organisation":"Lawyers Worldwide Magazine","year":2024,"award":"UK Reinsurance Law Firm of the Year – Experts in Law 2025"},{"organisation":"Corporate International","year":2024,"award":"UK Reinsurance Law Firm of the Year in England 2025"},{"organisation":"Lawyers Worldwide Annual Awards","year":2024,"award":"UK Reinsurance Law Firm of the Year"},{"organisation":"Global Business Awards","year":2024,"award":"Best Insurance Litigators UK"},{"organisation":"Corporate Livewire Innovation & Excellence Awards","year":2024,"award":"Insurance Law Firm of the Year"},{"organisation":"Who’s Who Legal","year":2023,"award":"Global Leaders in insurance & reinsurance - Stephen Carter / Bernadette Bailey / Bill Perry"},{"organisation":"Who’s Who Legal","year":2023,"award":"Global Leader in product liability defence - Bill Perry"},{"organisation":"Leaders League","year":2023,"award":"Best Law Firm for Insurance Litigation"},{"organisation":"Global 100","year":2023,"award":"Insurance & Reinsurance Law Firm of the Year UK"},{"organisation":"Corporate America Today Awards","year":2023,"award":"Insurance & Reinsurance Law Firm of the Year UK"},{"organisation":"Gamechangers Global Awards","year":2023,"award":"United Kingdom Lawyer of the Year (Insurance Litigation – Stephen Carter)"},{"organisation":"Worldwide Financial Advisor Excellence Awards","year":2023,"award":"Insurance & Reinsurance Law Firm of the Year UK"},{"organisation":"Global Law Experts","year":2023,"award":"Insurance & Reinsurance Law Firm of the Year in England"},{"organisation":"Chambers Guide UK & Chambers Global","year":2023,"award":"Leading Firm in Insurance:  Contentious Claims & Reinsurance"},{"organisation":"Chambers Global","year":2023,"award":"Insuralex – Leading Multi-Jurisdictional Network"},{"organisation":"Lawyers International’s Legal 100","year":2023,"award":"Insurance & Reinsurance Law Firm of the Year – UK"},{"organisation":"Lawyers Worldwide Awards","year":2023,"award":"Global Leading Lawyers"},{"organisation":"Lawyers Worldwide Superlawyers","year":2023,"award":"UK Reinsurance Law Firm of the Year"},{"organisation":"ACQ Five Awards","year":2023,"award":"United Kingdom – Lawyer of the Year (Insurance Litigation) – Stephen Carter"},{"organisation":"M&A Today","year":2023,"award":"Insurance & Reinsurance Law Firm of the Year"},{"organisation":"Acquisition International","year":2023,"award":"Leading Advisers"},{"organisation":"Who’s Who Legal","year":2022,"award":"Global Leaders in insurance & reinsurance - Stephen Carter / Bernadette Bailey /Bill Perry"},{"organisation":"Who’s Who Legal","year":2022,"award":"Global Leader in product liability defence - Bill Perry"},{"organisation":"Leaders League","year":2022,"award":"Best Law Firm for Insurance Litigation"},{"organisation":"Deal Makers Monthly","year":2022,"award":"Insurance & Reinsurance Law Firm of the Year UK"},{"organisation":"Global 100","year":2022,"award":"LInsurance & Reinsurance Law Firm of the Year UK"},{"organisation":"Gamechangers Global Awards","year":2022,"award":"Insurance & Reinsurance Litigation Law Firm of the Year UK"},{"organisation":"International Advisory Experts (IAE) Awards","year":2022,"award":"Insurance Law Award"},{"organisation":"Worldwide Financial Advisor Excellence Awards/Worldwide Financial Advisor Continent Awards","year":2022,"award":"Insurance & Reinsurance Lawyer of the Year UK – Stephen Carter"},{"organisation":"Global Law Experts","year":2022,"award":"Insurance & Reinsurance Law Firm of the Year in England"},{"organisation":"Chambers Guide UK & Chambers Global","year":2022,"award":"Leading Firm in Insurance:  Contentious Claims & Reinsurance"},{"organisation":"Chambers Global","year":2022,"award":"IInsuralex – Leading Multi-Jurisdictional Network"},{"organisation":"Lawyers International’s Legal 100","year":2022,"award":"Insurance & Reinsurance Law Firm of the Year – UK"},{"organisation":"Gamechangers Global Awards","year":2022,"award":"UK Lawyer of the Year – Insurance Litigation:  Stephen Carter"},{"organisation":"Gamechangers Global Awards","year":2022,"award":"London Law Firm of the Year"},{"organisation":"Gamechangers Global Awards","year":2022,"award":"UK Reinsurance – Arbitration Law Firm of the Year"},{"organisation":"Corporate International Awards","year":2022,"award":"Insurance & Reinsurance Law Firm of the Year in England"},{"organisation":"Who’s Who Legal","year":2021,"award":"Listed among the foremost legal practitioners in insurance & reinsurance - Stephen Carter / Bernadette Bailey / Bill Perry"},{"organisation":"Who’s Who Legal","year":2021,"award":"Listed among the foremost legal practitioners in product liability defence - Bill Perry"},{"organisation":"Who’s Who Legal","year":2021,"award":"Listed as “Thought Leaders” in insurance & reinsurance - Stephen Carter / Bernadette Bailey"},{"organisation":"Leaders League","year":2021,"award":"Highly Recommended in Insurance & Reinsurance"},{"organisation":"Lawyers Worldwide Awards","year":2021,"award":"Insurance & Reinsurance Law Firm of the Year UK"},{"organisation":"Global 100","year":2021,"award":"Insurance & Reinsurance Law Firm of the Year UK"},{"organisation":"Gamechangers Global Awards","year":2021,"award":"Insurance & Reinsurance Litigation Law Firm of the Year UK"},{"organisation":"International Advisory Experts (IAE) Awards","year":2021,"award":"Insurance Law Award"},{"organisation":"Gamechangers Country Awards","year":2021,"award":"Best Practice Operator of the Year in Insurance & Reinsurance"},{"organisation":"Worldwide Financial Advisor Excellence Awards","year":2021,"award":"Insurance & Reinsurance Law Firm of the Year UK"},{"organisation":"Lawyer Monthly","year":2021,"award":"Insurance & Reinsurance UK Award"},{"organisation":"Global Law Experts","year":2021,"award":"Insurance & Reinsurance Law Firm of the Year in England"},{"organisation":"Lawyers World Country Awards","year":2016,"award":"Reinsurance Law Firm of the Year: UK"},{"organisation":"AI Awards","year":2016,"award":"Most Innovative Law Firm UK"},{"organisation":"Lawyer International Legal 100 Awards","year":2016,"award":"Insurance &amp; Reinsurance Law Firm of the Year UK"},{"organisation":"Wealth &amp; Finance International Awards","year":2016,"award":"Best Niche Insurance Law Firm 2016 – Southern England"},{"organisation":"Wealth &amp; Finance International Awards","year":2016,"award":"Reinsurance Expert of the Year\\t- Stephen Carter"},{"organisation":"A1 Legal Awards","year":2016,"award":"Best Insurance &amp; Reinsurance Law – UK"},{"organisation":"Corporate Live Wire Awards","year":2016,"award":"Insurance &amp; Reinsurance Lawyer of the Year UK - Bill Perry"},{"organisation":"Corporate Live Wire Awards","year":2016,"award":"Boutique Insurance &amp; Reinsurance Law Firm Award"},{"organisation":"Intercontinental Finance &amp; Law Awards","year":2016,"award":"UK Reinsurance Law Firm of the Year"},{"organisation":"ICFM 500 Awards","year":2016,"award":"Leading Lawyer - Stephen Carter"},{"organisation":"ICFM 500 Awards)","year":2016,"award":"Leading Lawyer - Bill Perry"},{"organisation":"Dealmaker Global Awards","year":2016,"award":"Insurance &amp; Reinsurance Law Firm of the Year"},{"organisation":"M&A Today Global Award","year":2016,"award":"Insurance &amp; Reinsurance Law Firm of the Year UK"},{"organisation":"ICFM Country Awards","year":2016,"award":"Law Firm of the Year – Reinsurance &amp; Arbitration in the UK"},{"organisation":"AI Dispute Resolution Awards","year":2016,"award":"Best Insurance Litigation Boutique UK"},{"organisation":"Chambers Guide to the Legal Profession","year":2015,"award":"Leading Firm in Insurance Contentious Claims and Reinsurance"},{"organisation":"Chambers Guide to the Legal Profession","year":2015,"award":"Stephen Carter &amp; Bill Perry – Leading Individuals in Insurance Contentious Claims and Reinsurance"},{"organisation":"Legal 500","year":2015,"award":"Leading Firm in Insurance &amp; Reinsurance Litigation"},{"organisation":"Legal 500","year":2015,"award":"Leading Firm in Insurance, Corporate &amp; Regulatory"},{"organisation":"Legal 500","year":2015,"award":"Bill Perry &amp; Stephen Carter - Leading Individuals"},{"organisation":"Legal 500","year":2015,"award":"Bernadette Bailey – Recommended Lawyer"},{"organisation":"ICFM Law Awards","year":2015,"award":"UK Reinsurance Law Firm of the Year"},{"organisation":"Worldwide Financial Adviser Golden Globe Awards","year":2015,"award":"UK Reinsurance Law Firm of the Year"},{"organisation":"Lawyers World Global Awards","year":2015,"award":"Insurance &amp; Reinsurance Law Firm of the Year UK"},{"organisation":"PSN Annual International Awards","year":2015,"award":"Insurance &amp; Reinsurance Law Firm of the Year UK"},{"organisation":"Thompson Reuters \"Super Lawyers\"","year":2015,"award":"Stephen Carter, Bill Perry – \"Super Lawyers\""},{"organisation":"AI Global Awards","year":2015,"award":"Best Reinsurance Lawyer UK – Bill Perry"},{"organisation":"Corporate Vision Awards","year":2015,"award":"Sustained Excellence in Insurance UK"},{"organisation":"AI Legal Awards","year":2015,"award":"Insurance Law Firm of the Year UK"},{"organisation":"Global 100 Rankings","year":2015,"award":"Insurance &amp; Reinsurance Law Firm of the Year UK"},{"organisation":"Wealth &amp; Finance Intl – Insurance &amp; Reinsurance Awards","year":2014,"award":"Best Insurance &amp; Reinsurance Boutique Firm"},{"organisation":"Chambers Guide to the Legal Profession","year":2014,"award":"Leading Firm in Insurance Contentious Claims and Reinsurance"},{"organisation":"Chambers Guide to the Legal Profession","year":2014,"award":"Stephen Carter &amp; Bill Perry – Leading Individuals in Insurance Contentious Claims and Reinsurance"},{"organisation":"Legal 500","year":2014,"award":"Leading Firm in Insurance &amp; Reinsurance Litigation"},{"organisation":"Legal 500","year":2014,"award":"Leading Firm in Insurance, Corporate &amp; Regulatory"},{"organisation":"Legal 500","year":2014,"award":"Bill Perry &amp; Stephen Carter - Leading Individuals"},{"organisation":"Legal 500","year":2014,"award":"Bernadette Bailey – Recommended Lawyer"},{"organisation":"Worldwide Financial Advisor Awards Magazine","year":2014,"award":"UK Reinsurance Law Firm of the Year"},{"organisation":"Dealmakers Global Awards","year":2014,"award":"Insurance &amp; Reinsurance Law Firm of the Year UK"},{"organisation":"Wealth &amp; Finance Magazine, Business Awards","year":2014,"award":"Best for Insurance Disputes UK"},{"organisation":"ICFM 500 Awards","year":2014,"award":"Leading Lawyers – Top 500 in World"},{"organisation":"Who's Who Legal","year":2014,"award":"Stephen Carter – Insurance &amp; Reinsurance"},{"organisation":"M&amp;A Today Global Awards","year":2014,"award":"Insurance &amp; Reinsurance Law Firm of the Year (UK)"},{"organisation":"Intelligent Insurer's &quot;UK Legal Elite&quot;","year":2013,"award":"Overall Leaders - Commended<br>UK Claims - Highly Commended<br>UK Reinsurance - Commended<br>UK Individual Lawyers - Stephen Carter Commended"},{"organisation":"Chambers Guide to the Legal Profession","year":2013,"award":"Leading Firm in Insurance Contentious Claims and Reinsurance"},{"organisation":"Chambers Guide to the Legal Profession","year":2013,"award":"Stephen Carter and Bill Perry – Leading Individuals in Insurance Contentious Claims and Reinsurance"},{"organisation":"Lawyers World – Global Awards 2013","year":2013,"award":"UK Reinsurance Law Firm of the Year 2013"},{"organisation":"Legal 500","year":2013,"award":"Leading Firm in Insurance &amp; Reinsurance Litigation"},{"organisation":"Legal 500","year":2013,"award":"Leading Firm in Insurance, Corporate &amp; Regulatory"},{"organisation":"Legal 500","year":2013,"award":"Bill Perry &amp; Stephen Carter - Leading Individuals"},{"organisation":"Legal 500","year":2013,"award":"Bernadette Bailey – Recommended Lawyer"},{"organisation":"Corporate INTL Legal Awards","year":2013,"award":"Arbitration Law Firm of the Year in England"},{"organisation":"DealMakers End Of Year Annual Awards","year":2013,"award":"UK Reinsurance Law Firm of the Year 2013"},{"organisation":"Super Lawyers London 2013","year":2013,"award":"Bill Perry – Super Lawyer : Insurance Law"},{"organisation":"Lawyers World Law Awards","year":2013,"award":"UK Reinsurance Law Firm of the Year"},{"organisation":"Dealmakers Global Awards","year":2013,"award":"UK Reinsurance Law Firm of the Year"},{"organisation":"International Finance Magazine","year":2013,"award":"Bill Perry – Leading Lawyer 500 Winner"},{"organisation":"Acquisition International Awards","year":2012,"award":"UK Reinsurance Law Firm of the Year 2012"},{"organisation":"Legal 500","year":2012,"award":"Leading Firm in Insurance &amp; Reinsurance Litigation"},{"organisation":"Legal 500","year":2012,"award":"Leading Firm in Insurance, Corporate &amp; Regulatory"},{"organisation":"Legal 500 Insurance &amp; Reinsurance Litigation","year":2012,"award":"Bernadette Bailey: Recommended"},{"organisation":"Legal 500 Insurance, Corporate &amp; Regulatory","year":2012,"award":"Stephen Carter, Bernadette Bailey: Recommended"},{"organisation":"Chambers Guide to the Legal Profession","year":2012,"award":"Leading Firm in Insurance Contentious Claims &amp; Reinsurance"},{"organisation":"Chambers &amp; Partners Guide to the Legal Profession","year":2012,"award":"Stephen Carter, Bill Perry, Bernadette Bailey: Leading individuals in Insurance Contentious Claims &amp; Reinsurance"},{"organisation":"Legal 500","year":2012,"award":"Stephen Carter &amp; Bill Perry: Leading individuals in Insurance &amp; Reinsurance Litigation"},{"organisation":"Intelligent Insurer Survey","year":2012,"award":"Stephen Carter &amp; Bill Perry : Commended"},{"organisation":"Citywealth Leaders List 2012","year":2012,"award":"Bill Perry : Prominent Figure in &quot;Leading Lawyers – Contentious Trusts&quot;"},{"organisation":"International Who's Who of Product Liability Defence Lawyers","year":2012,"award":"Bill Perry : Listed Products Liability Defence Lawyer"},{"organisation":"The Lawyer Awards","year":2011,"award":"Niche Law Firm of the Year; Third Place (only insurance/reinsurance firm shortlisted)"},{"organisation":"Legal 500","year":2011,"award":"Stephen Carter &amp; Bill Perry: Leaders in their field"},{"organisation":"Intelligent Insurer Survey","year":2011,"award":"Stephen Carter: Leading Lawyer"},{"organisation":"Corporate International Legal Awards","year":2010,"award":"Insurance &amp; Reinsurance Law Firm of the Year 2010"},{"organisation":"Legal Business Awards","year":2010,"award":"Insurance Team of the Year: Highly Commended"},{"organisation":"Chambers Guide to the Legal Profession","year":2010,"award":"Leading Firm in Insurance Contentious Claims &amp; Reinsurance"}]